Tictactoe_anany/__init__.py
Tictactoe_anany-1.0.0.dist-info/WHEEL
Tictactoe_anany-1.0.0.dist-info/METADATA
Tictactoe_anany-1.0.0.dist-info/RECORD
