Metadata-Version: 2.1
Name: Tictactoe_anany
Version: 1.0.0
Summary: Tic Tac Toe game just for fun, made by Anany Singh
Home-page: UNKNOWN
License: UNKNOWN
Author: Anany Singh
Author-email: programmer.anany.singh@gmail.com
Classifier: License :: OSI Approved :: Apache Software License
